csv_optimizer/__init__.py
csv_optimizer/loader.py
csv_optimizer/setup.py
csv_optimizer-0.20.dist-info/METADATA
csv_optimizer-0.20.dist-info/WHEEL
csv_optimizer-0.20.dist-info/top_level.txt
csv_optimizer-0.20.dist-info/RECORD
