Metadata-Version: 2.1
Name: csv-optimizer
Version: 0.20
Summary: A Python package for efficiently loading CSV files with optimized data types.
Home-page: https://github.com/timmueller0/csv_optimizer
Author: Tim Müller
Author-email: timmueller0@gmail.com
Classifier: Programming Language :: Python :: 3
Classifier: License :: OSI Approved :: MIT License
Classifier: Operating System :: OS Independent
Requires-Python: >=3.6
Requires-Dist: pandas >=1.0.0
Requires-Dist: numpy >=1.18.0
